mini_scikit_learn/AdaBoost.py
mini_scikit_learn/DecisionTree.py
mini_scikit_learn/Estimator.py
mini_scikit_learn/KnnEstimator.py
mini_scikit_learn/LinearModel.py
mini_scikit_learn/LogisticRegression.py
mini_scikit_learn/ModelEnsembler.py
mini_scikit_learn/NBClassifier.py
mini_scikit_learn/NN.py
mini_scikit_learn/Predictor.py
mini_scikit_learn/RandomForest.py
mini_scikit_learn/SVM.py
mini_scikit_learn/__init__.py
mini_scikit_learn/main.py
mini_scikit_learn/test1.py
mini_scikit_learn/test2.py
mini_scikit_learn/test_ada.py
mini_scikit_learn/test_cv.py
mini_scikit_learn/test_dt.py
mini_scikit_learn/test_dtr.py
mini_scikit_learn/test_knn.py
mini_scikit_learn/test_lg.py
mini_scikit_learn/test_lgr.py
mini_scikit_learn/test_nb.py
mini_scikit_learn/test_nn.py
mini_scikit_learn/test_nn2.py
mini_scikit_learn/test_nn_digits.py
mini_scikit_learn/test_nn_iris.py
mini_scikit_learn/test_nn_random.py
mini_scikit_learn/test_nn_wine.py
mini_scikit_learn/test_rf.py
mini_scikit_learn/test_stacking.py
mini_scikit_learn/test_voting.py
mini_scikit_learn/metrics/__init__.py
mini_scikit_learn/metrics/metric.py
mini_scikit_learn/model_selection/GridSearch.py
mini_scikit_learn/model_selection/RandomSearch.py
mini_scikit_learn/model_selection/__init__.py
mini_scikit_learn/transformers/Encoders.py
mini_scikit_learn/transformers/Imputers.py
mini_scikit_learn/transformers/Transfomer.py
mini_scikit_learn/transformers/__init__.py
mini_scikit_learn/transformers/encoderTest.py
mini_scikit_learn/utils/Kfolds.py
mini_scikit_learn/utils/NeuralNetwork.py
mini_scikit_learn/utils/__init__.py
mini_scikit_learn/utils/cross_validation.py
mini_scikit_learn/utils/train_test_split.py
mini_scikit_learn-0.1.7.dist-info/METADATA
mini_scikit_learn-0.1.7.dist-info/WHEEL
mini_scikit_learn-0.1.7.dist-info/top_level.txt
mini_scikit_learn-0.1.7.dist-info/RECORD
