Metadata-Version: 2.1
Name: mini-scikit-learn
Version: 0.1.7
Summary: A brief description of your package
Home-page: https://github.com/YASSIRFRI/mini_scikit_learn.git
Author: Yassir Fri
Author-email: your.email@example.com
License: UNKNOWN
Platform: UNKNOWN
Classifier: Programming Language :: Python :: 3
Classifier: License :: OSI Approved :: MIT License
Classifier: Operating System :: OS Independent
Requires-Python: >=3.6
Requires-Dist: numpy
